tree_sitter_kotlin/__init__.py
tree_sitter_kotlin/__init__.pyi
tree_sitter_kotlin/_binding.pyd
tree_sitter_kotlin/binding.c
tree_sitter_kotlin/cli.py
tree_sitter_kotlin/py.typed
tree_sitter_kotlin/queries/highlights.scm
ts_kotlin-0.0.1.dist-info/LICENSE
ts_kotlin-0.0.1.dist-info/METADATA
ts_kotlin-0.0.1.dist-info/WHEEL
ts_kotlin-0.0.1.dist-info/entry_points.txt
ts_kotlin-0.0.1.dist-info/top_level.txt
ts_kotlin-0.0.1.dist-info/RECORD
